django_ftpserver/__init__.py
django_ftpserver/_unix.py
django_ftpserver/_windows.py
django_ftpserver/admin.py
django_ftpserver/authorizers.py
django_ftpserver/compat.py
django_ftpserver/daemonize.py
django_ftpserver/models.py
django_ftpserver/utils.py
django_ftpserver/management/__init__.py
django_ftpserver/management/commands/__init__.py
django_ftpserver/management/commands/createftpuseraccount.py
django_ftpserver/management/commands/createftpusergroup.py
django_ftpserver/management/commands/ftpserver.py
django_ftpserver/migrations/0001_initial.py
django_ftpserver/migrations/__init__.py
lab_django_ftpserver-0.3.5.1.dist-info/DESCRIPTION.rst
lab_django_ftpserver-0.3.5.1.dist-info/METADATA
lab_django_ftpserver-0.3.5.1.dist-info/RECORD
lab_django_ftpserver-0.3.5.1.dist-info/WHEEL
lab_django_ftpserver-0.3.5.1.dist-info/metadata.json
lab_django_ftpserver-0.3.5.1.dist-info/top_level.txt
