Metadata-Version: 2.0
Name: lab-django-ftpserver
Version: 0.3.5.1
Summary: FTP server application for Django.
Home-page: https://github.com/tokibito/django-ftpserver
Author: Shinya Okano
Author-email: tokibito@gmail.com
License: UNKNOWN
Platform: UNKNOWN
Classifier: Development Status :: 5 - Production/Stable
Classifier: Framework :: Django
Classifier: Programming Language :: Python :: 2.6
Classifier: Programming Language :: Python :: 2.7
Classifier: Programming Language :: Python :: 3.3
Classifier: Programming Language :: Python :: 3.4
Classifier: Programming Language :: Python :: 3.5
Classifier: License :: OSI Approved :: MIT License
Requires-Dist: Django (>=1.4)
Requires-Dist: pyftpdlib
